quail/__init__.py
quail/decode_speech.py
quail/distance.py
quail/egg.py
quail/fingerprint.py
quail/helpers.py
quail/load.py
quail/plot.py
quail/simulate.py
quail/analysis/__init__.py
quail/analysis/accuracy.py
quail/analysis/analysis.py
quail/analysis/clustering.py
quail/analysis/lagcrp.py
quail/analysis/pnr.py
quail/analysis/recmat.py
quail/analysis/spc.py
quail/data/README.md
quail/data/__init__.py
quail/data/automatic.egg
quail/data/cut_wordpool.csv
quail/data/manual.egg
quail/data/naturalistic.egg
quail-0.2.2.dist-info/LICENSE
quail-0.2.2.dist-info/METADATA
quail-0.2.2.dist-info/WHEEL
quail-0.2.2.dist-info/top_level.txt
quail-0.2.2.dist-info/RECORD
