Metadata-Version: 2.1
Name: quail
Version: 0.2.2
Summary: A python toolbox for analyzing and plotting free recall data
Home-page: https://github.com/ContextLab/quail
Author: Contextual Dynamics Lab
Author-email: contextualdynamics@gmail.com
License: MIT
License-File: LICENSE
Requires-Dist: numpy >=1.10.4
Requires-Dist: scipy >=0.17.1
Requires-Dist: matplotlib >=1.5.1
Requires-Dist: seaborn >=0.9.0
Requires-Dist: pandas >=0.24.0
Requires-Dist: future
Requires-Dist: six
Requires-Dist: deepdish
Requires-Dist: joblib
Provides-Extra: efficient-learning
Requires-Dist: sqlalchemy ; extra == 'efficient-learning'
Provides-Extra: speech-decoding
Requires-Dist: pydub ; extra == 'speech-decoding'
Requires-Dist: google-cloud-speech <0.31dev,>=0.30.0 ; extra == 'speech-decoding'
Requires-Dist: google-cloud <0.34.0,>=0.32.0 ; extra == 'speech-decoding'
